{
  "title": "Github Contribution Stats",
  "description": "动态生成 GitHub 贡献统计卡片！",
  "description:en-US": "Get your dynamically generated Github Contribution Stats!",
  "tag": {
    "repo": "https://github.com/LordDashMe/github-contribution-stats",
    "officialDoc": "https://github.com/LordDashMe/github-contribution-stats?tab=readme-ov-file#usage"
  },
  "linkRules": {
    "querys": [
      {
        "name": "username",
        "type": "string",
        "required": true,
        "description": "Github 用户名",
        "description:en-US": "Github username"
      }
    ],
    "uriTemplate": "https://github-contribution-stats.vercel.app/api/{?username}"
  },
  "examples": {
    "annotate": "LordDashMe",
    "alt": "贡献统计",
    "alt:en-US": "Contribution Stats",
    "href": "https://github-contribution-stats.vercel.app/api?username=LordDashMe",
    "images": [
      {
        "alt": "贡献统计",
        "alt:en-US": "Contribution Stats",
        "href": "https://github-contribution-stats.vercel.app/api?username=LordDashMe"
      }
    ]
  }
}